CTPv/__init__.py
CTPv/wx_helper.py
CTPv/Camera/Intrinsics.py
CTPv/Camera/__init__.py
CTPv/ICP/FastICP.py
CTPv/ICP/GeneralizedICP.py
CTPv/ICP/ICP.py
CTPv/ICP/ICP_wx.py
CTPv/ICP/__init__.py
CTPv/Plucker/Line.py
CTPv/Plucker/__init__.py
CTPv/Transformation/TransformationMatrix.py
CTPv/Transformation/__init__.py
ctpv-0.2.3.post3.dist-info/licenses/LICENSE
ctpv-0.2.3.post3.dist-info/METADATA
ctpv-0.2.3.post3.dist-info/WHEEL
ctpv-0.2.3.post3.dist-info/top_level.txt
ctpv-0.2.3.post3.dist-info/RECORD
