Metadata-Version: 2.4
Name: CTPv
Version: 0.2.3.post3
Summary: A toolbox of camera, Plücker, and transformation utilities
Author: Rhys Evans & Seppe Sels
Author-email: Rhys Evans & Seppe Sels <rhys.evans@uantwerpen.be>
License: MIT
Requires-Python: >=3.10
License-File: LICENSE
Requires-Dist: numpy
Requires-Dist: matplotlib
Requires-Dist: scipy
Requires-Dist: scikit-learn
Requires-Dist: open3d
Requires-Dist: plyfile
Requires-Dist: vispy
Requires-Dist: wxPython>=4.2.3; sys_platform != "linux"
Dynamic: author
Dynamic: license-file
Dynamic: requires-python
